{
  "generated": "2026-04-17T15:54:07.940495+00:00",
  "status": "ok",
  "history_span": "2026-04-03 \u2192 2026-04-17",
  "n_snapshots": 14,
  "trends": [
    {
      "metric": "total_flags",
      "label": "Total PIE Flags",
      "values": [
        247,
        249,
        251,
        30,
        30,
        30,
        221,
        223,
        223,
        243,
        242,
        258,
        275,
        276
      ],
      "dates": [
        "2026-04-03",
        "2026-04-04",
        "2026-04-05",
        "2026-04-06",
        "2026-04-07",
        "2026-04-08",
        "2026-04-09",
        "2026-04-10",
        "2026-04-11",
        "2026-04-13",
        "2026-04-14",
        "2026-04-15",
        "2026-04-16",
        "2026-04-17"
      ],
      "slope_per_day": 8.4747,
      "direction": "rising",
      "signal": "noisy",
      "r2": 0.1436,
      "current": 276,
      "unit": "flags"
    },
    {
      "metric": "critical_flags",
      "label": "Critical Severity Flags",
      "values": [
        39,
        40,
        41,
        0,
        0,
        0,
        41,
        40,
        40,
        54,
        49,
        51,
        54,
        55
      ],
      "dates": [
        "2026-04-03",
        "2026-04-04",
        "2026-04-05",
        "2026-04-06",
        "2026-04-07",
        "2026-04-08",
        "2026-04-09",
        "2026-04-10",
        "2026-04-11",
        "2026-04-13",
        "2026-04-14",
        "2026-04-15",
        "2026-04-16",
        "2026-04-17"
      ],
      "slope_per_day": 2.6022,
      "direction": "rising",
      "signal": "noisy",
      "r2": 0.2854,
      "current": 55,
      "unit": "flags"
    },
    {
      "metric": "ndaa_ratio",
      "label": "NDAA-Aligned Component Ratio",
      "values": [
        31.49,
        31.49,
        31.49,
        32.67,
        32.67,
        33.91,
        32.64,
        32.83,
        32.83,
        32.89,
        32.83,
        32.83,
        32.95,
        32.01
      ],
      "dates": [
        "2026-04-03",
        "2026-04-04",
        "2026-04-05",
        "2026-04-06",
        "2026-04-07",
        "2026-04-08",
        "2026-04-09",
        "2026-04-10",
        "2026-04-11",
        "2026-04-13",
        "2026-04-14",
        "2026-04-15",
        "2026-04-16",
        "2026-04-17"
      ],
      "slope_per_day": 0.0748,
      "direction": "rising",
      "signal": "noisy",
      "r2": 0.2076,
      "current": 32.01,
      "unit": "%"
    },
    {
      "metric": "parts_total",
      "label": "Total Components in DB",
      "values": [
        3890,
        3890,
        3890,
        3890,
        3890,
        4043,
        4044,
        4045,
        4045,
        3943,
        3951,
        3951,
        3960,
        4371
      ],
      "dates": [
        "2026-04-03",
        "2026-04-04",
        "2026-04-05",
        "2026-04-06",
        "2026-04-07",
        "2026-04-08",
        "2026-04-09",
        "2026-04-10",
        "2026-04-11",
        "2026-04-13",
        "2026-04-14",
        "2026-04-15",
        "2026-04-16",
        "2026-04-17"
      ],
      "slope_per_day": 18.178,
      "direction": "rising",
      "signal": "weak",
      "r2": 0.3532,
      "current": 4371,
      "unit": "components"
    },
    {
      "metric": "intel_velocity",
      "label": "Intel Article Velocity (7d rolling)",
      "values": [
        22.57,
        19.71,
        20.29,
        37.14,
        40.0,
        37.57,
        56.86,
        51.43,
        45.14,
        72.57,
        75.14,
        87.29,
        88.14,
        56.57
      ],
      "dates": [
        "2026-04-03",
        "2026-04-04",
        "2026-04-05",
        "2026-04-06",
        "2026-04-07",
        "2026-04-08",
        "2026-04-09",
        "2026-04-10",
        "2026-04-11",
        "2026-04-13",
        "2026-04-14",
        "2026-04-15",
        "2026-04-16",
        "2026-04-17"
      ],
      "slope_per_day": 4.9316,
      "direction": "rising",
      "signal": "moderate",
      "r2": 0.7829,
      "current": 56.57,
      "unit": "articles/day"
    },
    {
      "metric": "grayzone_anzu_robotics",
      "label": "Anzu Robotics Gray Zone Score",
      "values": [
        0.774,
        0.778,
        0.782,
        0.782,
        0.782,
        0.782,
        0.859,
        0.859,
        0.859,
        0.871,
        0.871,
        0.871,
        0.871,
        0.871
      ],
      "dates": [
        "2026-04-03",
        "2026-04-04",
        "2026-04-05",
        "2026-04-06",
        "2026-04-07",
        "2026-04-08",
        "2026-04-09",
        "2026-04-10",
        "2026-04-11",
        "2026-04-13",
        "2026-04-14",
        "2026-04-15",
        "2026-04-16",
        "2026-04-17"
      ],
      "slope_per_day": 0.0096,
      "direction": "stable",
      "signal": "archived",
      "r2": 0.813,
      "current": 0.871,
      "unit": "score",
      "entity": "Anzu Robotics",
      "entity_status": "discontinued"
    },
    {
      "metric": "grayzone_skyrover",
      "label": "SkyRover Gray Zone Score",
      "values": [
        0.854,
        0.854,
        0.854,
        0.854,
        0.854,
        0.854,
        0.854,
        0.854,
        0.854,
        0.862,
        0.857,
        0.857,
        0.857,
        0.857
      ],
      "dates": [
        "2026-04-03",
        "2026-04-04",
        "2026-04-05",
        "2026-04-06",
        "2026-04-07",
        "2026-04-08",
        "2026-04-09",
        "2026-04-10",
        "2026-04-11",
        "2026-04-13",
        "2026-04-14",
        "2026-04-15",
        "2026-04-16",
        "2026-04-17"
      ],
      "slope_per_day": 0.0004,
      "direction": "stable",
      "signal": "weak",
      "r2": 0.3938,
      "current": 0.857,
      "unit": "score",
      "entity": "SkyRover",
      "entity_status": "active"
    },
    {
      "metric": "grayzone_knowact",
      "label": "Knowact Gray Zone Score",
      "values": [
        0.854,
        0.854,
        0.854,
        0.854,
        0.854,
        0.854,
        0.854,
        0.854,
        0.854,
        0.857,
        0.857,
        0.857,
        0.857,
        0.857
      ],
      "dates": [
        "2026-04-03",
        "2026-04-04",
        "2026-04-05",
        "2026-04-06",
        "2026-04-07",
        "2026-04-08",
        "2026-04-09",
        "2026-04-10",
        "2026-04-11",
        "2026-04-13",
        "2026-04-14",
        "2026-04-15",
        "2026-04-16",
        "2026-04-17"
      ],
      "slope_per_day": 0.0003,
      "direction": "stable",
      "signal": "moderate",
      "r2": 0.6923,
      "current": 0.857,
      "unit": "score",
      "entity": "Knowact",
      "entity_status": "active"
    },
    {
      "metric": "grayzone_cogito_tech",
      "label": "Cogito Tech Gray Zone Score",
      "values": [
        0.856,
        0.856,
        0.856,
        0.856,
        0.856,
        0.856,
        0.856,
        0.856,
        0.856,
        0.856,
        0.856,
        0.856,
        0.856,
        0.856
      ],
      "dates": [
        "2026-04-03",
        "2026-04-04",
        "2026-04-05",
        "2026-04-06",
        "2026-04-07",
        "2026-04-08",
        "2026-04-09",
        "2026-04-10",
        "2026-04-11",
        "2026-04-13",
        "2026-04-14",
        "2026-04-15",
        "2026-04-16",
        "2026-04-17"
      ],
      "slope_per_day": 0.0,
      "direction": "stable",
      "signal": "strong",
      "r2": 1.0,
      "current": 0.856,
      "unit": "score",
      "entity": "Cogito Tech",
      "entity_status": "active"
    },
    {
      "metric": "grayzone_specta",
      "label": "SPECTA Gray Zone Score",
      "values": [
        0.856,
        0.856,
        0.856,
        0.856,
        0.856,
        0.856,
        0.856,
        0.856,
        0.856,
        0.856,
        0.856,
        0.859,
        0.859,
        0.859
      ],
      "dates": [
        "2026-04-03",
        "2026-04-04",
        "2026-04-05",
        "2026-04-06",
        "2026-04-07",
        "2026-04-08",
        "2026-04-09",
        "2026-04-10",
        "2026-04-11",
        "2026-04-13",
        "2026-04-14",
        "2026-04-15",
        "2026-04-16",
        "2026-04-17"
      ],
      "slope_per_day": 0.0002,
      "direction": "stable",
      "signal": "weak",
      "r2": 0.5077,
      "current": 0.859,
      "unit": "score",
      "entity": "SPECTA",
      "entity_status": "active"
    },
    {
      "metric": "grayzone_autel_robotics",
      "label": "Autel Robotics Gray Zone Score",
      "values": [
        0.517,
        0.521,
        0.525,
        0.525,
        0.525,
        0.525,
        0.868,
        0.868,
        0.868,
        0.868,
        0.868,
        0.868,
        0.868,
        0.868
      ],
      "dates": [
        "2026-04-03",
        "2026-04-04",
        "2026-04-05",
        "2026-04-06",
        "2026-04-07",
        "2026-04-08",
        "2026-04-09",
        "2026-04-10",
        "2026-04-11",
        "2026-04-13",
        "2026-04-14",
        "2026-04-15",
        "2026-04-16",
        "2026-04-17"
      ],
      "slope_per_day": 0.0365,
      "direction": "rising",
      "signal": "moderate",
      "r2": 0.743,
      "current": 0.868,
      "unit": "score",
      "entity": "Autel Robotics",
      "entity_status": "active"
    },
    {
      "metric": "grayzone_dji",
      "label": "DJI Gray Zone Score",
      "values": [
        0.903,
        0.903,
        0.903,
        0.903,
        0.903,
        0.903,
        0.903,
        0.897,
        0.897,
        0.897,
        0.899,
        0.899,
        0.899,
        0.899
      ],
      "dates": [
        "2026-04-03",
        "2026-04-04",
        "2026-04-05",
        "2026-04-06",
        "2026-04-07",
        "2026-04-08",
        "2026-04-09",
        "2026-04-10",
        "2026-04-11",
        "2026-04-13",
        "2026-04-14",
        "2026-04-15",
        "2026-04-16",
        "2026-04-17"
      ],
      "slope_per_day": -0.0005,
      "direction": "stable",
      "signal": "weak",
      "r2": 0.5627,
      "current": 0.899,
      "unit": "score",
      "entity": "DJI",
      "entity_status": "active"
    }
  ],
  "projections": [
    {
      "metric": "intel_velocity",
      "label": "News Coverage Trajectory",
      "direction": "rising",
      "signal": "moderate",
      "p30": 235.68,
      "p60": 383.63,
      "p90": 531.58,
      "confidence": 0.7829,
      "unit": "articles/day",
      "interpretation": "Intel velocity accelerating (+4.93 articles/day/day). Sector heating up \u2014 heightened monitoring recommended."
    },
    {
      "metric": "grayzone_autel_robotics",
      "label": "Autel Robotics Risk Trajectory",
      "entity": "Autel Robotics",
      "direction": "rising",
      "signal": "moderate",
      "p30": 1,
      "p60": 1,
      "p90": 1,
      "confidence": 0.743,
      "unit": "score",
      "interpretation": "Autel Robotics gray zone risk rising (+0.0365/day). Trajectory toward elevated risk tier \u2014 increased scrutiny warranted."
    },
    {
      "metric": "critical_flags",
      "label": "Critical Flag Trajectory",
      "direction": "rising",
      "signal": "noisy",
      "p30": 133.58,
      "p60": 211.65,
      "p90": 289.71,
      "confidence": 0.2854,
      "interpretation": "Critical flag count too noisy for reliable prediction."
    },
    {
      "metric": "ndaa_ratio",
      "label": "NDAA Compliance Trend",
      "direction": "rising",
      "signal": "noisy",
      "p30": 35.34,
      "p60": 37.59,
      "p90": 39.83,
      "confidence": 0.2076,
      "unit": "%",
      "interpretation": "NDAA ratio (32.0%) is noisy \u2014 need more history for reliable trend."
    },
    {
      "metric": "total_flags",
      "label": "PIE Flag Count",
      "direction": "rising",
      "signal": "noisy",
      "p30": 517.66,
      "p60": 771.9,
      "p90": 1026.14,
      "confidence": 0.1436,
      "interpretation": "Flag count is noisy \u2014 no clear trend yet. Continue accumulating daily snapshots."
    }
  ],
  "anomalies": []
}